selenium_move_cursor/MouseActions.py
selenium_move_cursor/__init__.py
selenium_move_cursor-0.0.8.dist-info/LICENSE.txt
selenium_move_cursor-0.0.8.dist-info/METADATA
selenium_move_cursor-0.0.8.dist-info/WHEEL
selenium_move_cursor-0.0.8.dist-info/top_level.txt
selenium_move_cursor-0.0.8.dist-info/RECORD
