Metadata-Version: 2.1
Name: selenium-move-cursor
Version: 0.0.8
Summary: Move mouse cursor to element in browser
Home-page: https://github.com/smirad91/SeleniumCursor
Author: smirad91
Author-email: smirad91@gmail.com
License: UNKNOWN
Platform: UNKNOWN
Classifier: Programming Language :: Python :: 3
Classifier: License :: OSI Approved :: MIT License
Classifier: Operating System :: Microsoft :: Windows :: Windows 10
Requires-Dist: pywin32
Requires-Dist: pyautogui
